streamlit_desktop_app/__init__.py
streamlit_desktop_app/__main__.py
streamlit_desktop_app/_version.py
streamlit_desktop_app/build.py
streamlit_desktop_app/cli.py
streamlit_desktop_app/core.py
streamlit_desktop_app/example.py
streamlit_desktop_app/py.typed
streamlit_desktop_app-0.3.3.dist-info/LICENSE
streamlit_desktop_app-0.3.3.dist-info/METADATA
streamlit_desktop_app-0.3.3.dist-info/WHEEL
streamlit_desktop_app-0.3.3.dist-info/entry_points.txt
streamlit_desktop_app-0.3.3.dist-info/RECORD
