Metadata-Version: 2.1
Name: streamlit-desktop-app
Version: 0.3.3
Summary: Easily convert Streamlit apps into standalone desktop applications.
Home-page: https://github.com/ohtaman/streamlit-desktop-app
License: Apache-2.0
Keywords: streamlit,desktop app,pywebview,pyinstaller
Author: ohtaman
Author-email: ohtamans@gmail.com
Requires-Python: >=3.9, !=2.7.*, !=3.0.*, !=3.1.*, !=3.2.*, !=3.3.*, !=3.4.*, !=3.5.*, !=3.6.*, !=3.7.*, !=3.8.*
Classifier: License :: OSI Approved :: Apache Software License
Classifier: Programming Language :: Python :: 3
Classifier: Programming Language :: Python :: 3.9
Classifier: Programming Language :: Python :: 3.10
Classifier: Programming Language :: Python :: 3.11
Classifier: Programming Language :: Python :: 3.12
Classifier: Programming Language :: Python :: 3.13
Requires-Dist: pyinstaller (>=6.11.1,<7.0.0)
Requires-Dist: pywebview (>=5.3.2,<6.0.0)
Requires-Dist: requests (>=2.32.3,<3.0.0)
Requires-Dist: streamlit (>=1.13.0)
Project-URL: Documentation, https://github.com/ohtaman/streamlit-desktop-app#readme
Project-URL: Repository, https://github.com/ohtaman/streamlit-desktop-app
